uniws/LICENSE
uniws/README.md
uniws/__init__.py
uniws/app.py
uniws/lib.py
uniws/shell.py
uniws/uniws.py
uniws/template/.gitattributes
uniws/template/.gitignore
uniws/template/.gitmodules
uniws/template/README.md
uniws/template/.uniws/.bashrc
uniws/template/.uniws/__init__.py
uniws/template/.uniws/hardware.py
uniws/template/.uniws/hwa.sh
uniws/template/.uniws/hwc.sh
uniws/template/.uniws/hwd.sh
uniws/template/.uniws/hwp.sh
uniws/template/.uniws/hws.sh
uniws/template/.uniws/hwu.sh
uniws/template/.uniws/software.py
uniws/template/.uniws/swa.sh
uniws/template/.uniws/swb.sh
uniws/template/.uniws/swc.sh
uniws/template/.uniws/swf.sh
uniws/template/.uniws/swi.sh
uniws/template/.uniws/swt.sh
uniws-0.7.4.dist-info/METADATA
uniws-0.7.4.dist-info/WHEEL
uniws-0.7.4.dist-info/entry_points.txt
uniws-0.7.4.dist-info/RECORD
