Metadata-Version: 2.1
Name: uniws
Version: 0.7.4
Summary: Python CLI and API for a uniform workspace
Project-URL: Repository, https://github.com/deohayer/uniws.git
Author-email: Deo Hayer <deohayer@mail.com>
Maintainer-email: Deo Hayer <deohayer@mail.com>
License: MIT License
Keywords: api,cli,development,workspace
Classifier: Development Status :: 3 - Alpha
Classifier: Intended Audience :: Developers
Classifier: License :: OSI Approved :: MIT License
Classifier: Operating System :: POSIX :: Linux
Classifier: Programming Language :: Python :: 3
Classifier: Programming Language :: Python :: 3.6
Classifier: Programming Language :: Python :: 3.7
Classifier: Programming Language :: Python :: 3.8
Classifier: Programming Language :: Python :: 3.9
Classifier: Programming Language :: Python :: 3.10
Classifier: Programming Language :: Python :: 3.11
Classifier: Topic :: Software Development
Requires-Python: >=3.6
Requires-Dist: argapp>=0.7
